bleak/__init__.py
bleak/__version__.py
bleak/exc.py
bleak/utils.py
bleak/uuids.py
bleak/backends/__init__.py
bleak/backends/client.py
bleak/backends/device.py
bleak/backends/bluezdbus/__init__.py
bleak/backends/bluezdbus/client.py
bleak/backends/bluezdbus/defs.py
bleak/backends/bluezdbus/discovery.py
bleak/backends/bluezdbus/signals.py
bleak/backends/bluezdbus/utils.py
bleak/backends/corebluetooth/__init__.py
bleak/backends/dotnet/BleakUWPBridge.dll
bleak/backends/dotnet/__init__.py
bleak/backends/dotnet/client.py
bleak/backends/dotnet/discovery.py
bleak/backends/dotnet/utils.py
bricknil_bleak-0.3.1.dist-info/AUTHORS.rst
bricknil_bleak-0.3.1.dist-info/LICENSE
bricknil_bleak-0.3.1.dist-info/METADATA
bricknil_bleak-0.3.1.dist-info/WHEEL
bricknil_bleak-0.3.1.dist-info/entry_points.txt
bricknil_bleak-0.3.1.dist-info/top_level.txt
bricknil_bleak-0.3.1.dist-info/RECORD
