Metadata-Version: 2.1
Name: bricknil-bleak
Version: 0.3.1
Summary: Bluetooth Low Energy platform Agnostic Klient
Home-page: https://github.com/virantha/bleak
Author: Virantha Ekanayake
Author-email: virantha@gmail.com
License: MIT
Platform: UNKNOWN
Classifier: Development Status :: 4 - Beta
Classifier: Framework :: AsyncIO
Classifier: Intended Audience :: Developers
Classifier: Topic :: Communications
Classifier: License :: OSI Approved :: MIT License
Classifier: Natural Language :: English
Classifier: Operating System :: Microsoft :: Windows :: Windows 10
Classifier: Operating System :: POSIX :: Linux
Classifier: Programming Language :: Python
Classifier: Programming Language :: Python :: 3
Classifier: Programming Language :: Python :: 3.5
Classifier: Programming Language :: Python :: 3.6
Classifier: Programming Language :: Python :: 3.7
Classifier: Programming Language :: Python :: Implementation :: CPython
Requires-Dist: pyobjc ; platform_system == "Darwin"
Requires-Dist: pyobjc-framework-CoreBluetooth ; platform_system == "Darwin"
Requires-Dist: txdbus ; platform_system == "Linux"
Requires-Dist: pythonnet ; platform_system == "Windows"
